dbbasic_compiler/__init__.py
dbbasic_compiler/cli.py
dbbasic_compiler/compiler.py
dbbasic_compiler-0.1.0.dist-info/licenses/LICENSE
dbbasic_compiler-0.1.0.dist-info/METADATA
dbbasic_compiler-0.1.0.dist-info/WHEEL
dbbasic_compiler-0.1.0.dist-info/entry_points.txt
dbbasic_compiler-0.1.0.dist-info/top_level.txt
dbbasic_compiler-0.1.0.dist-info/RECORD
