Metadata-Version: 2.4
Name: dbbasic-compiler
Version: 0.1.0
Summary: The compiler that understands English
Home-page: https://github.com/askrobots/dbbasic-compiler
Author: DBBasic
Author-email: DBBasic <hello@dbbasic.com>
License: MIT
Project-URL: Homepage, https://github.com/askrobots/dbbasic-compiler
Project-URL: Documentation, https://github.com/askrobots/dbbasic-compiler#readme
Project-URL: Repository, https://github.com/askrobots/dbbasic-compiler
Project-URL: Issues, https://github.com/askrobots/dbbasic-compiler/issues
Keywords: compiler,ai,natural-language,dbbasic
Classifier: Development Status :: 3 - Alpha
Classifier: Intended Audience :: Developers
Classifier: Topic :: Software Development :: Compilers
Classifier: License :: OSI Approved :: MIT License
Classifier: Programming Language :: Python :: 3
Classifier: Programming Language :: Python :: 3.7
Classifier: Programming Language :: Python :: 3.8
Classifier: Programming Language :: Python :: 3.9
Classifier: Programming Language :: Python :: 3.10
Classifier: Programming Language :: Python :: 3.11
Requires-Python: >=3.7
License-File: LICENSE
Requires-Dist: anthropic>=0.18.0
Dynamic: author
Dynamic: home-page
Dynamic: license-file
Dynamic: requires-python
